README
setup.py
ncalc/__init__.py
ncalc/eval.py
ncalc.egg-info/PKG-INFO
ncalc.egg-info/SOURCES.txt
ncalc.egg-info/dependency_links.txt
ncalc.egg-info/top_level.txt