Metadata-Version: 1.1
Name: ncalc
Version: 1.0
Summary: Allows evaluate math expression represented as string.
Home-page: UNKNOWN
Author: Artem Yaschenko
Author-email: ayaschenko@yahoo.com
License: GPL
Keywords: math expression evaluate string
Platform: UNKNOWN
Classifier: Development Status :: 5 - Production/Stable
Classifier: Environment :: Console
Classifier: Intended Audience :: Developers
Classifier: Intended Audience :: Education
Classifier: Intended Audience :: Science/Research
Classifier: License :: Freeware
